mm_cryptography/__init__.py
mm_cryptography/fernet.py
mm_cryptography/openssl.py
mm_cryptography/py.typed
mm_cryptography/cli/__init__.py
mm_cryptography/cli/fernet_commands.py
mm_cryptography/cli/main.py
mm_cryptography/cli/openssl_commands.py
mm_cryptography/cli/utils.py
mm_cryptography-0.1.1.dist-info/METADATA
mm_cryptography-0.1.1.dist-info/WHEEL
mm_cryptography-0.1.1.dist-info/entry_points.txt
mm_cryptography-0.1.1.dist-info/RECORD
